<?xml version="1.0" encoding="UTF-8"?>
<objects serializationModel="Studio.02.02.00">
	<object class="AudioFile" id="{e1ef7699-a61b-41f4-bbbd-e33627af06ed}">
		<property name="assetPath">
			<value>uicide-boys-type-scream-fx.wav</value>
		</property>
		<property name="frequencyInKHz">
			<value>48</value>
		</property>
		<property name="channelCount">
			<value>2</value>
		</property>
		<property name="length">
			<value>7.9090833333333332</value>
		</property>
		<relationship name="masterAssetFolder">
			<destination>{dc57212d-36bb-4246-9aa4-0f4354d14550}</destination>
		</relationship>
	</object>
</objects>
